.gitignore
CHANGES.rst
INSTALL.rst
LICENSE.txt
MANIFEST.in
README.rst
SUPPORT.rst
setup.py
terms.vim
Terms.egg-info/PKG-INFO
Terms.egg-info/SOURCES.txt
Terms.egg-info/dependency_links.txt
Terms.egg-info/entry_points.txt
Terms.egg-info/namespace_packages.txt
Terms.egg-info/requires.txt
Terms.egg-info/top_level.txt
doc/conf.py
doc/contact.rst
doc/godel.rst
doc/index.rst
doc/install.rst
doc/language.rst
doc/protocol.rst
doc/theory.rst
doc/usage.rst
doc/terms-theme/genindex.html
doc/terms-theme/layout.html
doc/terms-theme/page.html
doc/terms-theme/search.html
doc/terms-theme/theme.conf
doc/terms-theme/static/bootstrap.zip
doc/terms-theme/static/css/bootstrap-responsive.css
doc/terms-theme/static/css/bootstrap.css
doc/terms-theme/static/css/docs.css
doc/terms-theme/static/ico/apple-touch-icon-114-precomposed.png
doc/terms-theme/static/ico/apple-touch-icon-57-precomposed.png
doc/terms-theme/static/ico/apple-touch-icon-72-precomposed.png
doc/terms-theme/static/ico/favicon.ico
doc/terms-theme/static/img/bird.png
doc/terms-theme/static/img/bootstrap-mdo-sfmoma-01.jpg
doc/terms-theme/static/img/bootstrap-mdo-sfmoma-02.jpg
doc/terms-theme/static/img/bootstrap-mdo-sfmoma-03.jpg
doc/terms-theme/static/img/browsers.png
doc/terms-theme/static/img/fade_top.png
doc/terms-theme/static/img/github-16px.png
doc/terms-theme/static/img/glyphicons-halflings-white.png
doc/terms-theme/static/img/glyphicons-halflings.png
doc/terms-theme/static/img/grid-18px-masked.png
doc/terms-theme/static/img/icon-css3.png
doc/terms-theme/static/img/icon-github.png
doc/terms-theme/static/img/icon-html5.png
doc/terms-theme/static/img/icon-twitter.png
doc/terms-theme/static/img/less-logo-large.png
doc/terms-theme/static/img/less-small.png
doc/terms-theme/static/img/responsive-illustrations.png
doc/terms-theme/static/img/example-sites/fleetio.png
doc/terms-theme/static/img/example-sites/jshint.png
doc/terms-theme/static/img/example-sites/kippt.png
doc/terms-theme/static/img/example-sites/soundready.png
doc/terms-theme/static/img/examples/bootstrap-example-fluid.jpg
doc/terms-theme/static/img/examples/bootstrap-example-hero.jpg
doc/terms-theme/static/img/examples/bootstrap-example-starter.jpg
