Metadata-Version: 1.1
Name: Terms
Version: 0.1.0b23
Summary: A rule production system
Home-page: http://terms.readthedocs.org/en/latest/
Author: Enrique Perez Arnaud
Author-email: enriquepablo@gmail.com
License: GNU GENERAL PUBLIC LICENSE Version 3
Platform: UNKNOWN
Classifier: Development Status :: 4 - Beta
Classifier: Intended Audience :: Developers
Classifier: License :: OSI Approved :: GNU General Public License v3 (GPLv3)
Classifier: Operating System :: POSIX
Classifier: Programming Language :: Python :: 3
Classifier: Topic :: Scientific/Engineering
